coshsh/__init__.py
coshsh/application.py
coshsh/configparser.py
coshsh/contact.py
coshsh/contactgroup.py
coshsh/datainterface.py
coshsh/datarecipient.py
coshsh/datasource.py
coshsh/dependency.py
coshsh/generator.py
coshsh/host.py
coshsh/hostgroup.py
coshsh/item.py
coshsh/jinja2_extensions.py
coshsh/monitoringdetail.py
coshsh/recipe.py
coshsh/templaterule.py
coshsh/util.py
coshsh/vault.py
coshsh-11.1.data/data/recipes/default/classes/contact_defaults.py
coshsh-11.1.data/data/recipes/default/classes/datarecipient_coshsh_default.py
coshsh-11.1.data/data/recipes/default/classes/datarecipient_discard.py
coshsh-11.1.data/data/recipes/default/classes/datarecipient_prometheus_snmp.py
coshsh-11.1.data/data/recipes/default/classes/datasource_csvfile.py
coshsh-11.1.data/data/recipes/default/classes/datasource_discard.py
coshsh-11.1.data/data/recipes/default/classes/datasource_simplesample.py
coshsh-11.1.data/data/recipes/default/classes/detail_access.py
coshsh-11.1.data/data/recipes/default/classes/detail_custom_macro.py
coshsh-11.1.data/data/recipes/default/classes/detail_datastore.py
coshsh-11.1.data/data/recipes/default/classes/detail_depth.py
coshsh-11.1.data/data/recipes/default/classes/detail_filesystem.py
coshsh-11.1.data/data/recipes/default/classes/detail_interface.py
coshsh-11.1.data/data/recipes/default/classes/detail_keyvalues.py
coshsh-11.1.data/data/recipes/default/classes/detail_login.py
coshsh-11.1.data/data/recipes/default/classes/detail_loginsnmpv2.py
coshsh-11.1.data/data/recipes/default/classes/detail_loginsnmpv3.py
coshsh-11.1.data/data/recipes/default/classes/detail_nagios.py
coshsh-11.1.data/data/recipes/default/classes/detail_nagiosconf.py
coshsh-11.1.data/data/recipes/default/classes/detail_port.py
coshsh-11.1.data/data/recipes/default/classes/detail_process.py
coshsh-11.1.data/data/recipes/default/classes/detail_role.py
coshsh-11.1.data/data/recipes/default/classes/detail_socket.py
coshsh-11.1.data/data/recipes/default/classes/detail_tablespace.py
coshsh-11.1.dist-info/licenses/LICENSE
coshsh-11.1.dist-info/METADATA
coshsh-11.1.dist-info/WHEEL
coshsh-11.1.dist-info/top_level.txt
coshsh-11.1.dist-info/RECORD
