Metadata-Version: 2.4
Name: coshsh
Version: 11.1
Summary: Coshsh - config generator for monitoring systems
Home-page: http://github.com/lausser/coshsh
Author: Gerhard Lausser
Author-email: gerhard.lausser@consol.de
License: AGPLv3
Keywords: nagios,icinga,naemon,shinken,prometheus,monitoring
License-File: LICENSE
Dynamic: author
Dynamic: author-email
Dynamic: description
Dynamic: description-content-type
Dynamic: home-page
Dynamic: keywords
Dynamic: license
Dynamic: license-file
Dynamic: summary
